KivyCalendar/__init__.py
KivyCalendar/calendar_data.py
KivyCalendar/calendar_ui.py
kivycalendar3/__init__.py
kivycalendar3/calendar_data.py
kivycalendar3/calendar_ui.py
kivycalendar3-0.0.2.dist-info/COPYING
kivycalendar3-0.0.2.dist-info/METADATA
kivycalendar3-0.0.2.dist-info/WHEEL
kivycalendar3-0.0.2.dist-info/top_level.txt
kivycalendar3-0.0.2.dist-info/RECORD
